src/decoder.v
// ========================================================
// Sub-module: 8-to-256 Decoder
// ========================================================
module decoder_8_256 (
    input  wire [7:0]   in_addr,
    input  wire         en,
    output reg  [255:0] out_data
);
    always @(*) begin
        out_data = 256'd0;
        if (en) begin
            // Synthesizable dynamic bit-shift for decoding
            out_data[in_addr] = 1'b1; 
        end
    end
endmodule

// ========================================================
// Top-module: 10-to-1024 Decoder (Wrapper)
// ========================================================
module decoder_10_1024 (
    input  wire [9:0]    in_addr,
    input  wire          en,
    output wire [1023:0] out_data
);
    // 2-to-4 pre-decoding logic for block enables
    wire en0 = en & (in_addr[9:8] == 2'b00);
    wire en1 = en & (in_addr[9:8] == 2'b01);
    wire en2 = en & (in_addr[9:8] == 2'b10);
    wire en3 = en & (in_addr[9:8] == 2'b11);

    // Instantiate four 8:256 decoders
    decoder_8_256 dec0 (
        .in_addr(in_addr[7:0]), 
        .en(en0), 
        .out_data(out_data[255:0])
    );
    
    decoder_8_256 dec1 (
        .in_addr(in_addr[7:0]), 
        .en(en1), 
        .out_data(out_data[511:256])
    );
    
    decoder_8_256 dec2 (
        .in_addr(in_addr[7:0]), 
        .en(en2), 
        .out_data(out_data[767:512])
    );
    
    decoder_8_256 dec3 (
        .in_addr(in_addr[7:0]), 
        .en(en3), 
        .out_data(out_data[1023:768])
    );
endmodule

src/decoder_tb.v
`timescale 1ns/1ps

module tb_decoder_10_1024;

    // Inputs to DUT
    reg [9:0] in_addr;
    reg       en;

    // Outputs from DUT
    wire [1023:0] out_data;

    integer i;
    integer errors = 0;

    // Instantiate the Device Under Test (DUT)
    decoder_10_1024 dut (
        .in_addr(in_addr),
        .en(en),
        .out_data(out_data)
    );

    initial begin
        // Setup waveform dumping for GTKWave
        $dumpfile("tb_decoder.vcd");
        $dumpvars(0, tb_decoder_10_1024);

        $display("Starting 10:1024 Decoder Simulation...");

        // --- TEST 1: Enable is LOW ---
        // The output MUST remain completely zero regardless of the address
        en = 1'b0;
        in_addr = 10'd500; // Arbitrary address
        #10;
        
        if (out_data !== 1024'b0) begin
            $display("ERROR: Output bus is not zero when EN=0.");
            errors = errors + 1;
        end else begin
            $display("PASS: Enable LOW test handled correctly.");
        end
        #10;

        // --- TEST 2: Exhaustive Address Sweep (EN = 1) ---
        // We test every single address from 0 to 1023
        $display("Sweeping all 1024 addresses with EN=1...");
        en = 1'b1;
        for (i = 0; i < 1024; i = i + 1) begin
            in_addr = i[9:0];
            #1; // Wait 1 timestep for the combinational logic to resolve

            // The output should be exactly '1' shifted left by 'i' positions.
            // If any other bit is high, or the target bit is low, it fails.
            if (out_data !== (1024'b1 << i)) begin
                $display("ERROR at address %0d: Incorrect decode.", i);
                errors = errors + 1;
            end
        end
        $display("Sweep complete.");
        #10;

        // --- TEST 3: Dynamic Enable Toggle ---
        // Ensure the decoder can turn on and off rapidly at a specific address
        $display("Testing dynamic Enable toggle at address 850...");
        in_addr = 10'd850;
        
        en = 1'b1; #10;
        if (out_data[850] !== 1'b1) errors = errors + 1;
        
        en = 1'b0; #10; // Turn it off
        if (out_data !== 1024'b0) errors = errors + 1;
        
        en = 1'b1; #10; // Turn it back on
        if (out_data[850] !== 1'b1) errors = errors + 1;

        if (errors == 0) $display("PASS: Dynamic toggle handled correctly.");

        // --- FINAL RESULTS ---
        #10;
        if (errors == 0) begin
            $display("======================================");
            $display("          ALL TESTS PASSED!           ");
            $display("======================================");
        end else begin
            $display("======================================");
            $display("      TESTS FAILED with %0d errors.   ", errors);
            $display("======================================");
        end

        $finish;
    end

endmodule

src/tb_decoder.vcd
$date
	Thu Jun 25 21:11:48 2026
$end
$version
	Icarus Verilog
$end
$timescale
	1ps
$end
$scope module tb_decoder_10_1024 $end
$var wire 1024 ! out_data [1023:0] $end
$var reg 1 " en $end
$var reg 10 # in_addr [9:0] $end
$var integer 32 $ errors [31:0] $end
$var integer 32 % i [31:0] $end
$scope module dut $end
$var wire 1 " en $end
$var wire 1 & en0 $end
$var wire 1 ' en1 $end
$var wire 1 ( en2 $end
$var wire 1 ) en3 $end
$var wire 10 * in_addr [9:0] $end
$var wire 1024 + out_data [1023:0] $end
$scope module dec0 $end
$var wire 1 & en $end
$var wire 8 , in_addr [7:0] $end
$var reg 256 - out_data [255:0] $end
$upscope $end
$scope module dec1 $end
$var wire 1 ' en $end
$var wire 8 . in_addr [7:0] $end
$var reg 256 / out_data [255:0] $end
$upscope $end
$scope module dec2 $end
$var wire 1 ( en $end
$var wire 8 0 in_addr [7:0] $end
$var reg 256 1 out_data [255:0] $end
$upscope $end
$scope module dec3 $end
$var wire 1 ) en $end
$var wire 8 2 in_addr [7:0] $end
$var reg 256 3 out_data [255:0] $end
$upscope $end
$upscope $end
$upscope $end
$enddefinitions $end
$comment Show the parameter values. $end
$dumpall
$end
#0
$dumpvars
b0 3
b11110100 2
b0 1
b11110100 0
b0 /
b11110100 .
b0 -
b11110100 ,
b0 +
b111110100 *
0)
0(
0'
0&
bx %
b0 $
b111110100 #
0"
b0 !
$end
#20000
b1 -
1&
b1 !
b1 +
b0 /
b0 ,
b0 .
b0 0
b0 2
0'
b0 #
b0 *
b0 %
1"
#21000
b10 !
b10 +
b10 -
b1 ,
b1 .
b1 0
b1 2
b1 #
b1 *
b1 %
#22000
b100 !
b100 +
b100 -
b10 ,
b10 .
b10 0
b10 2
b10 #
b10 *
b10 %
#23000
b1000 !
b1000 +
b1000 -
b11 ,
b11 .
b11 0
b11 2
b11 #
b11 *
b11 %
#24000
b10000 !
b10000 +
b10000 -
b100 ,
b100 .
b100 0
b100 2
b100 #
b100 *
b100 %
#25000
b100000 !
b100000 +
b100000 -
b101 ,
b101 .
b101 0
b101 2
b101 #
b101 *
b101 %
#26000
b1000000 !
b1000000 +
b1000000 -
b110 ,
b110 .
b110 0
b110 2
b110 #
b110 *
b110 %
#27000
b10000000 !
b10000000 +
b10000000 -
b111 ,
b111 .
b111 0
b111 2
b111 #
b111 *
b111 %
#28000
b100000000 !
b100000000 +
b100000000 -
b1000 ,
b1000 .
b1000 0
b1000 2
b1000 #
b1000 *
b1000 %
#29000
b1000000000 !
b1000000000 +
b1000000000 -
b1001 ,
b1001 .
b1001 0
b1001 2
b1001 #
b1001 *
b1001 %
#30000
b10000000000 !
b10000000000 +
b10000000000 -
b1010 ,
b1010 .
b1010 0
b1010 2
b1010 #
b1010 *
b1010 %
#31000
b100000000000 !
b100000000000 +
b100000000000 -
b1011 ,
b1011 .
b1011 0
b1011 2
b1011 #
b1011 *
b1011 %
#32000
b1000000000000 !
b1000000000000 +
b1000000000000 -
b1100 ,
b1100 .
b1100 0
b1100 2
b1100 #
b1100 *
b1100 %
#33000
b10000000000000 !
b10000000000000 +
b10000000000000 -
b1101 ,
b1101 .
b1101 0
b1101 2
b1101 #
b1101 *
b1101 %
#34000
b100000000000000 !
b100000000000000 +
b100000000000000 -
b1110 ,
b1110 .
b1110 0
b1110 2
b1110 #
b1110 *
b1110 %
#35000
b1000000000000000 !
b1000000000000000 +
b1000000000000000 -
b1111 ,
b1111 .
b1111 0
b1111 2
b1111 #
b1111 *
b1111 %
#36000
b10000000000000000 !
b10000000000000000 +
b10000000000000000 -
b10000 ,
b10000 .
b10000 0
b10000 2
b10000 #
b10000 *
b10000 %
#37000
b100000000000000000 !
b100000000000000000 +
b100000000000000000 -
b10001 ,
b10001 .
b10001 0
b10001 2
b10001 #
b10001 *
b10001 %
#38000
b1000000000000000000 !
b1000000000000000000 +
b1000000000000000000 -
b10010 ,
b10010 .
b10010 0
b10010 2
b10010 #
b10010 *
b10010 %
#39000
b10000000000000000000 !
b10000000000000000000 +
b10000000000000000000 -
b10011 ,
b10011 .
b10011 0
b10011 2
b10011 #
b10011 *
b10011 %
#40000
b100000000000000000000 !
b100000000000000000000 +
b100000000000000000000 -
b10100 ,
b10100 .
b10100 0
b10100 2
b10100 #
b10100 *
b10100 %
#41000
b1000000000000000000000 !
b1000000000000000000000 +
b1000000000000000000000 -
b10101 ,
b10101 .
b10101 0
b10101 2
b10101 #
b10101 *
b10101 %
#42000
b10000000000000000000000 !
b10000000000000000000000 +
b10000000000000000000000 -
b10110 ,
b10110 .
b10110 0
b10110 2
b10110 #
b10110 *
b10110 %
#43000
b100000000000000000000000 !
b100000000000000000000000 +
b100000000000000000000000 -
b10111 ,
b10111 .
b10111 0
b10111 2
b10111 #
b10111 *
b10111 %
#44000
b1000000000000000000000000 !
b1000000000000000000000000 +
b1000000000000000000000000 -
b11000 ,
b11000 .
b11000 0
b11000 2
b11000 #
b11000 *
b11000 %
#45000
b10000000000000000000000000 !
b10000000000000000000000000 +
b10000000000000000000000000 -
b11001 ,
b11001 .
b11001 0
b11001 2
b11001 #
b11001 *
b11001 %
#46000
b100000000000000000000000000 !
b100000000000000000000000000 +
b100000000000000000000000000 -
b11010 ,
b11010 .
b11010 0
b11010 2
b11010 #
b11010 *
b11010 %
#47000
b1000000000000000000000000000 !
b1000000000000000000000000000 +
b1000000000000000000000000000 -
b11011 ,
b11011 .
b11011 0
b11011 2
b11011 #
b11011 *
b11011 %
#48000
b10000000000000000000000000000 !
b10000000000000000000000000000 +
b10000000000000000000000000000 -
b11100 ,
b11100 .
b11100 0
b11100 2
b11100 #
b11100 *
b11100 %
#49000
b100000000000000000000000000000 !
b100000000000000000000000000000 +
b100000000000000000000000000000 -
b11101 ,
b11101 .
b11101 0
b11101 2
b11101 #
b11101 *
b11101 %
#50000
b1000000000000000000000000000000 !
b1000000000000000000000000000000 +
b1000000000000000000000000000000 -
b11110 ,
b11110 .
b11110 0
b11110 2
b11110 #
b11110 *
b11110 %
#51000
b10000000000000000000000000000000 !
b10000000000000000000000000000000 +
b10000000000000000000000000000000 -
b11111 ,
b11111 .
b11111 0
b11111 2
b11111 #
b11111 *
b11111 %
#52000
b100000000000000000000000000000000 !
b100000000000000000000000000000000 +
b100000000000000000000000000000000 -
b100000 ,
b100000 .
b100000 0
b100000 2
b100000 #
b100000 *
b100000 %
#53000
b1000000000000000000000000000000000 !
b1000000000000000000000000000000000 +
b1000000000000000000000000000000000 -
b100001 ,
b100001 .
b100001 0
b100001 2
b100001 #
b100001 *
b100001 %
#54000
b10000000000000000000000000000000000 !
b10000000000000000000000000000000000 +
b10000000000000000000000000000000000 -
b100010 ,
b100010 .
b100010 0
b100010 2
b100010 #
b100010 *
b100010 %
#55000
b100000000000000000000000000000000000 !
b100000000000000000000000000000000000 +
b100000000000000000000000000000000000 -
b100011 ,
b100011 .
b100011 0
b100011 2
b100011 #
b100011 *
b100011 %
#56000
b1000000000000000000000000000000000000 !
b1000000000000000000000000000000000000 +
b1000000000000000000000000000000000000 -
b100100 ,
b100100 .
b100100 0
b100100 2
b100100 #
b100100 *
b100100 %
#57000
b10000000000000000000000000000000000000 !
b10000000000000000000000000000000000000 +
b10000000000000000000000000000000000000 -
b100101 ,
b100101 .
b100101 0
b100101 2
b100101 #
b100101 *
b100101 %
#58000
b100000000000000000000000000000000000000 !
b100000000000000000000000000000000000000 +
b100000000000000000000000000000000000000 -
b100110 ,
b100110 .
b100110 0
b100110 2
b100110 #
b100110 *
b100110 %
#59000
b1000000000000000000000000000000000000000 !
b1000000000000000000000000000000000000000 +
b1000000000000000000000000000000000000000 -
b100111 ,
b100111 .
b100111 0
b100111 2
b100111 #
b100111 *
b100111 %
#60000
b10000000000000000000000000000000000000000 !
b10000000000000000000000000000000000000000 +
b10000000000000000000000000000000000000000 -
b101000 ,
b101000 .
b101000 0
b101000 2
b101000 #
b101000 *
b101000 %
#61000
b100000000000000000000000000000000000000000 !
b100000000000000000000000000000000000000000 +
b100000000000000000000000000000000000000000 -
b101001 ,
b101001 .
b101001 0
b101001 2
b101001 #
b101001 *
b101001 %
#62000
b1000000000000000000000000000000000000000000 !
b1000000000000000000000000000000000000000000 +
b1000000000000000000000000000000000000000000 -
b101010 ,
b101010 .
b101010 0
b101010 2
b101010 #
b101010 *
b101010 %
#63000
b10000000000000000000000000000000000000000000 !
b10000000000000000000000000000000000000000000 +
b10000000000000000000000000000000000000000000 -
b101011 ,
b101011 .
b101011 0
b101011 2
b101011 #
b101011 *
b101011 %
#64000
b100000000000000000000000000000000000000000000 !
b100000000000000000000000000000000000000000000 +
b100000000000000000000000000000000000000000000 -
b101100 ,
b101100 .
b101100 0
b101100 2
b101100 #
b101100 *
b101100 %
#65000
b1000000000000000000000000000000000000000000000 !
b1000000000000000000000000000000000000000000000 +
b1000000000000000000000000000000000000000000000 -
b101101 ,
b101101 .
b101101 0
b101101 2
b101101 #
b101101 *
b101101 %
#66000
b10000000000000000000000000000000000000000000000 !
b10000000000000000000000000000000000000000000000 +
b10000000000000000000000000000000000000000000000 -
b101110 ,
b101110 .
b101110 0
b101110 2
b101110 #
b101110 *
b101110 %
#67000
b100000000000000000000000000000000000000000000000 !
b100000000000000000000000000000000000000000000000 +
b100000000000000000000000000000000000000000000000 -
b101111 ,
b101111 .
b101111 0
b101111 2
b101111 #
b101111 *
b101111 %
#68000
b1000000000000000000000000000000000000000000000000 !
b1000000000000000000000000000000000000000000000000 +
b1000000000000000000000000000000000000000000000000 -
b110000 ,
b110000 .
b110000 0
b110000 2
b110000 #
b110000 *
b110000 %
#69000
b10000000000000000000000000000000000000000000000000 !
b10000000000000000000000000000000000000000000000000 +
b10000000000000000000000000000000000000000000000000 -
b110001 ,
b110001 .
b110001 0
b110001 2
b110001 #
b110001 *
b110001 %
#70000
b100000000000000000000000000000000000000000000000000 !
b100000000000000000000000000000000000000000000000000 +
b100000000000000000000000000000000000000000000000000 -
b110010 ,
b110010 .
b110010 0
b110010 2
b110010 #
b110010 *
b110010 %
#71000
b1000000000000000000000000000000000000000000000000000 !
b1000000000000000000000000000000000000000000000000000 +
b1000000000000000000000000000000000000000000000000000 -
b110011 ,
b110011 .
b110011 0
b110011 2
b110011 #
b110011 *
b110011 %
#72000
b10000000000000000000000000000000000000000000000000000 !
b10000000000000000000000000000000000000000000000000000 +
b10000000000000000000000000000000000000000000000000000 -
b110100 ,
b110100 .
b110100 0
b110100 2
b110100 #
b110100 *
b110100 %
#73000
b100000000000000000000000000000000000000000000000000000 !
b100000000000000000000000000000000000000000000000000000 +
b100000000000000000000000000000000000000000000000000000 -
b110101 ,
b110101 .
b110101 0
b110101 2
b110101 #
b110101 *
b110101 %
#74000
b1000000000000000000000000000000000000000000000000000000 !
b1000000000000000000000000000000000000000000000000000000 +
b1000000000000000000000000000000000000000000000000000000 -
b110110 ,
b110110 .
b110110 0
b110110 2
b110110 #
b110110 *
b110110 %
#75000
b10000000000000000000000000000000000000000000000000000000 !
b10000000000000000000000000000000000000000000000000000000 +
b10000000000000000000000000000000000000000000000000000000 -
b110111 ,
b110111 .
b110111 0
b110111 2
b110111 #
b110111 *
b110111 %
#76000
b100000000000000000000000000000000000000000000000000000000 !
b100000000000000000000000000000000000000000000000000000000 +
b100000000000000000000000000000000000000000000000000000000 -
b111000 ,
b111000 .
b111000 0
b111000 2
b111000 #
b111000 *
b111000 %
#77000
b1000000000000000000000000000000000000000000000000000000000 !
b1000000000000000000000000000000000000000000000000000000000 +
b1000000000000000000000000000000000000000000000000000000000 -
b111001 ,
b111001 .
b111001 0
b111001 2
b111001 #
b111001 *
b111001 %
#78000
b10000000000000000000000000000000000000000000000000000000000 !
b10000000000000000000000000000000000000000000000000000000000 +
b10000000000000000000000000000000000000000000000000000000000 -
b111010 ,
b111010 .
b111010 0
b111010 2
b111010 #
b111010 *
b111010 %
#79000
b100000000000000000000000000000000000000000000000000000000000 !
b100000000000000000000000000000000000000000000000000000000000 +
b100000000000000000000000000000000000000000000000000000000000 -
b111011 ,
b111011 .
b111011 0
b111011 2
b111011 #
b111011 *
b111011 %
#80000
b1000000000000000000000000000000000000000000000000000000000000 !
b1000000000000000000000000000000000000000000000000000000000000 +
b1000000000000000000000000000000000000000000000000000000000000 -
b111100 ,
b111100 .
b111100 0
b111100 2
b111100 #
b111100 *
b111100 %
#81000
b10000000000000000000000000000000000000000000000000000000000000 !
b10000000000000000000000000000000000000000000000000000000000000 +
b10000000000000000000000000000000000000000000000000000000000000 -
b111101 ,
b111101 .
b111101 0
b111101 2
b111101 #
b111101 *
b111101 %
#82000
b100000000000000000000000000000000000000000000000000000000000000 !
b100000000000000000000000000000000000000000000000000000000000000 +
b100000000000000000000000000000000000000000000000000000000000000 -
b111110 ,
b111110 .
b111110 0
b111110 2
b111110 #
b111110 *
b111110 %
#83000
b1000000000000000000000000000000000000000000000000000000000000000 !
b1000000000000000000000000000000000000000000000000000000000000000 +
b1000000000000000000000000000000000000000000000000000000000000000 -
b111111 ,
b111111 .
b111111 0
b111111 2
b111111 #
b111111 *
b111111 %
#84000
b10000000000000000000000000000000000000000000000000000000000000000 !
b10000000000000000000000000000000000000000000000000000000000000000 +
b10000000000000000000000000000000000000000000000000000000000000000 -
b1000000 ,
b1000000 .
b1000000 0
b1000000 2
b1000000 #
b1000000 *
b1000000 %
#85000
b100000000000000000000000000000000000000000000000000000000000000000 !
b100000000000000000000000000000000000000000000000000000000000000000 +
b100000000000000000000000000000000000000000000000000000000000000000 -
b1000001 ,
b1000001 .
b1000001 0
b1000001 2
b1000001 #
b1000001 *
b1000001 %
#86000
b1000000000000000000000000000000000000000000000000000000000000000000 !
b1000000000000000000000000000000000000000000000000000000000000000000 +
b1000000000000000000000000000000000000000000000000000000000000000000 -
b1000010 ,
b1000010 .
b1000010 0
b1000010 2
b1000010 #
b1000010 *
b1000010 %
#87000
b10000000000000000000000000000000000000000000000000000000000000000000 !
b10000000000000000000000000000000000000000000000000000000000000000000 +
b10000000000000000000000000000000000000000000000000000000000000000000 -
b1000011 ,
b1000011 .
b1000011 0
b1000011 2
b1000011 #
b1000011 *
b1000011 %
#88000
b100000000000000000000000000000000000000000000000000000000000000000000 !
b100000000000000000000000000000000000000000000000000000000000000000000 +
b100000000000000000000000000000000000000000000000000000000000000000000 -
b1000100 ,
b1000100 .
b1000100 0
b1000100 2
b1000100 #
b1000100 *
b1000100 %
#89000
b1000000000000000000000000000000000000000000000000000000000000000000000 !
b1000000000000000000000000000000000000000000000000000000000000000000000 +
b1000000000000000000000000000000000000000000000000000000000000000000000 -
b1000101 ,
b1000101 .
b1000101 0
b1000101 2
b1000101 #
b1000101 *
b1000101 %
#90000
b10000000000000000000000000000000000000000000000000000000000000000000000 !
b10000000000000000000000000000000000000000000000000000000000000000000000 +
b10000000000000000000000000000000000000000000000000000000000000000000000 -
b1000110 ,
b1000110 .
b1000110 0
b1000110 2
b1000110 #
b1000110 *
b1000110 %
#91000
b100000000000000000000000000000000000000000000000000000000000000000000000 !
b100000000000000000000000000000000000000000000000000000000000000000000000 +
b100000000000000000000000000000000000000000000000000000000000000000000000 -
b1000111 ,
b1000111 .
b1000111 0
b1000111 2
b1000111 #
b1000111 *
b1000111 %
#92000
b1000000000000000000000000000000000000000000000000000000000000000000000000 !
b1000000000000000000000000000000000000000000000000000000000000000000000000 +
b1000000000000000000000000000000000000000000000000000000000000000000000000 -
b1001000 ,
b1001000 .
b1001000 0
b1001000 2
b1001000 #
b1001000 *
b1001000 %
#93000
b10000000000000000000000000000000000000000000000000000000000000000000000000 !
b10000000000000000000000000000000000000000000000000000000000000000000000000 +
b10000000000000000000000000000000000000000000000000000000000000000000000000 -
b1001001 ,
b1001001 .
b1001001 0
b1001001 2
b1001001 #
b1001001 *
b1001001 %
#94000
b100000000000000000000000000000000000000000000000000000000000000000000000000 !
b100000000000000000000000000000000000000000000000000000000000000000000000000 +
b100000000000000000000000000000000000000000000000000000000000000000000000000 -
b1001010 ,
b1001010 .
b1001010 0
b1001010 2
b1001010 #
b1001010 *
b1001010 %
#95000
b1000000000000000000000000000000000000000000000000000000000000000000000000000 !
b1000000000000000000000000000000000000000000000000000000000000000000000000000 +
b1000000000000000000000000000000000000000000000000000000000000000000000000000 -
b1001011 ,
b1001011 .
b1001011 0
b1001011 2
b1001011 #
b1001011 *
b1001011 %
#96000
b10000000000000000000000000000000000000000000000000000000000000000000000000000 !
b10000000000000000000000000000000000000000000000000000000000000000000000000000 +
b10000000000000000000000000000000000000000000000000000000000000000000000000000 -
b1001100 ,
b1001100 .
b1001100 0
b1001100 2
b1001100 #
b1001100 *
b1001100 %
#97000
b100000000000000000000000000000000000000000000000000000000000000000000000000000 !
b100000000000000000000000000000000000000000000000000000000000000000000000000000 +
b100000000000000000000000000000000000000000000000000000000000000000000000000000 -
b1001101 ,
b1001101 .
b1001101 0
b1001101 2
b1001101 #
b1001101 *
b1001101 %
#98000
b1000000000000000000000000000000000000000000000000000000000000000000000000000000 !
b1000000000000000000000000000000000000000000000000000000000000000000000000000000 +
b1000000000000000000000000000000000000000000000000000000000000000000000000000000 -
b1001110 ,
b1001110 .
b1001110 0
b1001110 2
b1001110 #
b1001110 *
b1001110 %
#99000
b10000000000000000000000000000000000000000000000000000000000000000000000000000000 !
b10000000000000000000000000000000000000000000000000000000000000000000000000000000 +
b10000000000000000000000000000000000000000000000000000000000000000000000000000000 -
b1001111 ,
b1001111 .
b1001111 0
b1001111 2
b1001111 #
b1001111 *
b1001111 %
#100000
b100000000000000000000000000000000000000000000000000000000000000000000000000000000 !
b100000000000000000000000000000000000000000000000000000000000000000000000000000000 +
b100000000000000000000000000000000000000000000000000000000000000000000000000000000 -
b1010000 ,
b1010000 .
b1010000 0
b1010000 2
b1010000 #
b1010000 *
b1010000 %
#101000
b1000000000000000000000000000000000000000000000000000000000000000000000000000000000 !
b1000000000000000000000000000000000000000000000000000000000000000000000000000000000 +
b1000000000000000000000000000000000000000000000000000000000000000000000000000000000 -
b1010001 ,
b1010001 .
b1010001 0
b1010001 2
b1010001 #
b1010001 *
b1010001 %
#102000
b10000000000000000000000000000000000000000000000000000000000000000000000000000000000 !
b10000000000000000000000000000000000000000000000000000000000000000000000000000000000 +
b10000000000000000000000000000000000000000000000000000000000000000000000000000000000 -
b1010010 ,
b1010010 .
b1010010 0
b1010010 2
b1010010 #
b1010010 *
b1010010 %
#103000
b100000000000000000000000000000000000000000000000000000000000000000000000000000000000 !
b100000000000000000000000000000000000000000000000000000000000000000000000000000000000 +
b100000000000000000000000000000000000000000000000000000000000000000000000000000000000 -
b1010011 ,
b1010011 .
b1010011 0
b1010011 2
b1010011 #
b1010011 *
b1010011 %
#104000
b1000000000000000000000000000000000000000000000000000000000000000000000000000000000000 !
b1000000000000000000000000000000000000000000000000000000000000000000000000000000000000 +
b1000000000000000000000000000000000000000000000000000000000000000000000000000000000000 -
b1010100 ,
b1010100 .
b1010100 0
b1010100 2
b1010100 #
b1010100 *
b1010100 %
#105000
b10000000000000000000000000000000000000000000000000000000000000000000000000000000000000 !
b10000000000000000000000000000000000000000000000000000000000000000000000000000000000000 +
b10000000000000000000000000000000000000000000000000000000000000000000000000000000000000 -
b1010101 ,
b1010101 .
b1010101 0
b1010101 2
b1010101 #
b1010101 *
b1010101 %
#106000
b100000000000000000000000000000000000000000000000000000000000000000000000000000000000000 !
b100000000000000000000000000000000000000000000000000000000000000000000000000000000000000 +
b100000000000000000000000000000000000000000000000000000000000000000000000000000000000000 -
b1010110 ,
b1010110 .
b1010110 0
b1010110 2
b1010110 #
b1010110 *
b1010110 %
#107000
b1000000000000000000000000000000000000000000000000000000000000000000000000000000000000000 !
b1000000000000000000000000000000000000000000000000000000000000000000000000000000000000000 +
b1000000000000000000000000000000000000000000000000000000000000000000000000000000000000000 -
b1010111 ,
b1010111 .
b1010111 0
b1010111 2
b1010111 #
b1010111 *
b1010111 %
#108000
b10000000000000000000000000000000000000000000000000000000000000000000000000000000000000000 !
b10000000000000000000000000000000000000000000000000000000000000000000000000000000000000000 +
b10000000000000000000000000000000000000000000000000000000000000000000000000000000000000000 -
b1011000 ,
b1011000 .
b1011000 0
b1011000 2
b1011000 #
b1011000 *
b1011000 %
#109000
b100000000000000000000000000000000000000000000000000000000000000000000000000000000000000000 !
b100000000000000000000000000000000000000000000000000000000000000000000000000000000000000000 +
b100000000000000000000000000000000000000000000000000000000000000000000000000000000000000000 -
b1011001 ,
b1011001 .
b1011001 0
b1011001 2
b1011001 #
b1011001 *
b1011001 %
#110000
b1000000000000000000000000000000000000000000000000000000000000000000000000000000000000000000 !
b1000000000000000000000000000000000000000000000000000000000000000000000000000000000000000000 +
b1000000000000000000000000000000000000000000000000000000000000000000000000000000000000000000 -
b1011010 ,
b1011010 .
b1011010 0
b1011010 2
b1011010 #
b1011010 *
b1011010 %
#111000
b10000000000000000000000000000000000000000000000000000000000000000000000000000000000000000000 !
b10000000000000000000000000000000000000000000000000000000000000000000000000000000000000000000 +
b10000000000000000000000000000000000000000000000000000000000000000000000000000000000000000000 -
b1011011 ,
b1011011 .
b1011011 0
b1011011 2
b1011011 #
b1011011 *
b1011011 %
#112000
b100000000000000000000000000000000000000000000000000000000000000000000000000000000000000000000 !
b100000000000000000000000000000000000000000000000000000000000000000000000000000000000000000000 +
b100000000000000000000000000000000000000000000000000000000000000000000000000000000000000000000 -
b1011100 ,
b1011100 .
b1011100 0
b1011100 2
b1011100 #
b1011100 *
b1011100 %
#113000
b1000000000000000000000000000000000000000000000000000000000000000000000000000000000000000000000 !
b1000000000000000000000000000000000000000000000000000000000000000000000000000000000000000000000 +
b1000000000000000000000000000000000000000000000000000000000000000000000000000000000000000000000 -
b1011101 ,
b1011101 .
b1011101 0
b1011101 2
b1011101 #
b1011101 *
b1011101 %
#114000
b10000000000000000000000000000000000000000000000000000000000000000000000000000000000000000000000 !
b10000000000000000000000000000000000000000000000000000000000000000000000000000000000000000000000 +
b10000000000000000000000000000000000000000000000000000000000000000000000000000000000000000000000 -
b1011110 ,
b1011110 .
b1011110 0
b1011110 2
b1011110 #
b1011110 *
b1011110 %
#115000
b100000000000000000000000000000000000000000000000000000000000000000000000000000000000000000000000 !
b100000000000000000000000000000000000000000000000000000000000000000000000000000000000000000000000 +
b100000000000000000000000000000000000000000000000000000000000000000000000000000000000000000000000 -
b1011111 ,
b1011111 .
b1011111 0
b1011111 2
b1011111 #
b1011111 *
b1011111 %
#116000
b1000000000000000000000000000000000000000000000000000000000000000000000000000000000000000000000000 !
b1000000000000000000000000000000000000000000000000000000000000000000000000000000000000000000000000 +
b1000000000000000000000000000000000000000000000000000000000000000000000000000000000000000000000000 -
b1100000 ,
b1100000 .
b1100000 0
b1100000 2
b1100000 #
b1100000 *
b1100000 %
#117000
b10000000000000000000000000000000000000000000000000000000000000000000000000000000000000000000000000 !
b10000000000000000000000000000000000000000000000000000000000000000000000000000000000000000000000000 +
b10000000000000000000000000000000000000000000000000000000000000000000000000000000000000000000000000 -
b1100001 ,
b1100001 .
b1100001 0
b1100001 2
b1100001 #
b1100001 *
b1100001 %
#118000
b100000000000000000000000000000000000000000000000000000000000000000000000000000000000000000000000000 !
b100000000000000000000000000000000000000000000000000000000000000000000000000000000000000000000000000 +
b100000000000000000000000000000000000000000000000000000000000000000000000000000000000000000000000000 -
b1100010 ,
b1100010 .
b1100010 0
b1100010 2
b1100010 #
b1100010 *
b1100010 %
#119000
b1000000000000000000000000000000000000000000000000000000000000000000000000000000000000000000000000000 !
b1000000000000000000000000000000000000000000000000000000000000000000000000000000000000000000000000000 +
b1000000000000000000000000000000000000000000000000000000000000000000000000000000000000000000000000000 -
b1100011 ,
b1100011 .
b1100011 0
b1100011 2
b1100011 #
b1100011 *
b1100011 %
#120000
b10000000000000000000000000000000000000000000000000000000000000000000000000000000000000000000000000000 !
b10000000000000000000000000000000000000000000000000000000000000000000000000000000000000000000000000000 +
b10000000000000000000000000000000000000000000000000000000000000000000000000000000000000000000000000000 -
b1100100 ,
b1100100 .
b1100100 0
b1100100 2
b1100100 #
b1100100 *
b1100100 %
#121000
b100000000000000000000000000000000000000000000000000000000000000000000000000000000000000000000000000000 !
b100000000000000000000000000000000000000000000000000000000000000000000000000000000000000000000000000000 +
b100000000000000000000000000000000000000000000000000000000000000000000000000000000000000000000000000000 -
b1100101 ,
b1100101 .
b1100101 0
b1100101 2
b1100101 #
b1100101 *
b1100101 %
#122000
b1000000000000000000000000000000000000000000000000000000000000000000000000000000000000000000000000000000 !
b1000000000000000000000000000000000000000000000000000000000000000000000000000000000000000000000000000000 +
b1000000000000000000000000000000000000000000000000000000000000000000000000000000000000000000000000000000 -
b1100110 ,
b1100110 .
b1100110 0
b1100110 2
b1100110 #
b1100110 *
b1100110 %
#123000
b10000000000000000000000000000000000000000000000000000000000000000000000000000000000000000000000000000000 !
b10000000000000000000000000000000000000000000000000000000000000000000000000000000000000000000000000000000 +
b10000000000000000000000000000000000000000000000000000000000000000000000000000000000000000000000000000000 -
b1100111 ,
b1100111 .
b1100111 0
b1100111 2
b1100111 #
b1100111 *
b1100111 %
#124000
b100000000000000000000000000000000000000000000000000000000000000000000000000000000000000000000000000000000 !
b100000000000000000000000000000000000000000000000000000000000000000000000000000000000000000000000000000000 +
b100000000000000000000000000000000000000000000000000000000000000000000000000000000000000000000000000000000 -
b1101000 ,
b1101000 .
b1101000 0
b1101000 2
b1101000 #
b1101000 *
b1101000 %
#125000
b1000000000000000000000000000000000000000000000000000000000000000000000000000000000000000000000000000000000 !
b1000000000000000000000000000000000000000000000000000000000000000000000000000000000000000000000000000000000 +
b1000000000000000000000000000000000000000000000000000000000000000000000000000000000000000000000000000000000 -
b1101001 ,
b1101001 .
b1101001 0
b1101001 2
b1101001 #
b1101001 *
b1101001 %
#126000
b10000000000000000000000000000000000000000000000000000000000000000000000000000000000000000000000000000000000 !
b10000000000000000000000000000000000000000000000000000000000000000000000000000000000000000000000000000000000 +
b10000000000000000000000000000000000000000000000000000000000000000000000000000000000000000000000000000000000 -
b1101010 ,
b1101010 .
b1101010 0
b1101010 2
b1101010 #
b1101010 *
b1101010 %
